xjx7773/__init__.py
xjx7773/xjx7773.py
xjx7773/face_sdk_detect_landmark/__init__.py
face_sdk_detect_landmark-0.0.1.dist-info/LICENSE
face_sdk_detect_landmark-0.0.1.dist-info/METADATA
face_sdk_detect_landmark-0.0.1.dist-info/WHEEL
face_sdk_detect_landmark-0.0.1.dist-info/top_level.txt
face_sdk_detect_landmark-0.0.1.dist-info/RECORD
